invoke/__init__.py
invoke/__main__.py
invoke/_version.py
invoke/collection.py
invoke/config.py
invoke/context.py
invoke/env.py
invoke/exc_new.py
invoke/exc_old.py
invoke/exceptions.py
invoke/executor.py
invoke/loader.py
invoke/main.py
invoke/program.py
invoke/runners.py
invoke/tasks.py
invoke/terminals.py
invoke/util.py
invoke/watchers.py
invoke/completion/__init__.py
invoke/completion/__init__.pyc
invoke/completion/bash.completion
invoke/completion/complete.py
invoke/completion/complete.pyc
invoke/completion/fish.completion
invoke/completion/zsh.completion
invoke/completion/__pycache__/__init__.cpython-310.pyc
invoke/completion/__pycache__/__init__.cpython-37.pyc
invoke/completion/__pycache__/__init__.cpython-38-pytest-5.3.5.pyc
invoke/completion/__pycache__/__init__.cpython-38.pyc
invoke/completion/__pycache__/complete.cpython-27-PYTEST.pyc
invoke/completion/__pycache__/complete.cpython-310.pyc
invoke/completion/__pycache__/complete.cpython-37-PYTEST.pyc
invoke/completion/__pycache__/complete.cpython-37.pyc
invoke/completion/__pycache__/complete.cpython-38-PYTEST.pyc
invoke/completion/__pycache__/complete.cpython-38-pytest-5.3.5.pyc
invoke/completion/__pycache__/complete.cpython-38.pyc
invoke/parser/__init__.py
invoke/parser/argument.py
invoke/parser/context.py
invoke/parser/parser.py
invoke/vendor/__init__.py
invoke/vendor/decorator.py
invoke/vendor/six.py
invoke/vendor/fluidity/__init__.py
invoke/vendor/fluidity/backwardscompat.py
invoke/vendor/fluidity/machine.py
invoke/vendor/lexicon/__init__.py
invoke/vendor/lexicon/alias_dict.py
invoke/vendor/lexicon/attribute_dict.py
invoke/vendor/yaml2/__init__.py
invoke/vendor/yaml2/composer.py
invoke/vendor/yaml2/constructor.py
invoke/vendor/yaml2/cyaml.py
invoke/vendor/yaml2/dumper.py
invoke/vendor/yaml2/emitter.py
invoke/vendor/yaml2/error.py
invoke/vendor/yaml2/events.py
invoke/vendor/yaml2/loader.py
invoke/vendor/yaml2/nodes.py
invoke/vendor/yaml2/parser.py
invoke/vendor/yaml2/reader.py
magicinvoke-2.4.6.dist-info/LICENSE
magicinvoke-2.4.6.dist-info/METADATA
magicinvoke-2.4.6.dist-info/WHEEL
magicinvoke-2.4.6.dist-info/entry_points.txt
magicinvoke-2.4.6.dist-info/top_level.txt
magicinvoke-2.4.6.dist-info/RECORD
